{
  "alpinevpn": {
    "description": "Alpine 3.18",
    "hide": false,
    "last_updated": "2024-02-08T07:50:48.000Z",
    "last_updated_url": "https://github.com/hotio/base/actions/runs/7826413273",
    "latest": false,
    "tags": [
      "alpinevpn",
      "alpinevpn-20240208074855",
      "alpinevpn-3a29cfb"
    ]
  },
  "jammyvpn": {
    "description": "Ubuntu 22.04",
    "hide": false,
    "last_updated": "2024-02-08T07:50:19.000Z",
    "last_updated_url": "https://github.com/hotio/base/actions/runs/7826389500",
    "latest": false,
    "tags": [
      "jammyvpn",
      "jammyvpn-20240208074555",
      "jammyvpn-37608c8"
    ]
  }
}
